ttt_game/__init__.py
ttt_game/game.py
ttt_game-0.1.0.dist-info/LICENCE
ttt_game-0.1.0.dist-info/METADATA
ttt_game-0.1.0.dist-info/WHEEL
ttt_game-0.1.0.dist-info/top_level.txt
ttt_game-0.1.0.dist-info/RECORD
