Metadata-Version: 2.1
Name: ttt-game
Version: 0.1.0
Summary: A simple tic tac toe game implementation
Home-page: https://github.com/dm1sh/ttt-game
Author: dm1sh
Author-email: me@dmitriy.icu
License: UNKNOWN
Project-URL: Bug Tracker, https://github.com/dm1sh/ttt-game/issues
Platform: UNKNOWN
Classifier: Programming Language :: Python :: 3
Classifier: License :: OSI Approved :: MIT License
Classifier: Operating System :: OS Independent
Requires-Python: >=3.6
License-File: LICENCE
